{
  "goals": [
    {
      "id": "a57c",
      "name": "JACKED AF",
      "category": "Health",
      "description": "I want to get that beach body i've always been saying and the first step is getting the right equipment, maybe a start pack which is like 20k.",
      "targetAmount": 25000,
      "savedAmount": 5000,
      "deadline": "2025-12-01",
      "createdAt": "2025-07-20T11:06:04.697Z"
    },
    {
      "id": "84b6",
      "name": "God's Work",
      "category": "Spiritual",
      "description": "We need t build a new local church, i want contribute atleast a millionby next year.",
      "targetAmount": 1000000,
      "savedAmount": 50000,
      "deadline": "2026-07-20",
      "createdAt": "2025-07-20T11:10:47.360Z"
    },
    {
      "id": "d15a",
      "name": "SuperMan Tool Box",
      "category": "Hobbies & Interests",
      "description": "There is this ultimate tool box that any self proclaimed handy man could do, i have to get it",
      "targetAmount": 30000,
      "savedAmount": 8290,
      "deadline": "2025-12-27",
      "createdAt": "2025-07-20T17:10:31.113Z"
    },
    {
      "id": "5c6d",
      "name": "CHRISTMAS DINNER!!!",
      "category": "Social Life",
      "description": "We will be hosting the extended family for christmas this year, and it ain't free",
      "targetAmount": 25000,
      "savedAmount": 7250,
      "deadline": "2025-12-20",
      "createdAt": "2025-07-20T17:48:28.211Z"
    },
    {
      "id": "b307",
      "name": "JAMAICA BABY!!!",
      "category": "Travel & Leisure",
      "description": "This is the year we finally breathe while we celebrate 15 years in marriage",
      "targetAmount": 120000,
      "savedAmount": 80000,
      "deadline": "2025-10-10",
      "createdAt": "2025-07-20T17:50:59.689Z"
    }
  ]
}
